README.md
setup.py
djangox/__init__.py
djangox.egg-info/PKG-INFO
djangox.egg-info/SOURCES.txt
djangox.egg-info/dependency_links.txt
djangox.egg-info/top_level.txt
djangox/apps/__init__.py
djangox/apps/bs4tl/__init__.py
djangox/apps/bs4tl/static/bs4tl.css
djangox/apps/bs4tl/templates/bs4tl/dialog.html
djangox/apps/bs4tl/templates/bs4tl/forms.html
djangox/apps/bs4tl/templates/bs4tl/list.html
djangox/apps/bs4tl/templates/bs4tl/nav.html
djangox/apps/bs4tl/templates/bs4tl/not_found.html
djangox/apps/bs4tl/templates/bs4tl/paginator.html
djangox/apps/bs4tl/templates/bs4tl/permission_denied.html
djangox/apps/bs4tl/templates/bs4tl/server_error.html
djangox/apps/tools/__init__.py
djangox/apps/tools/management/__init__.py
djangox/apps/tools/management/commands/__init__.py
djangox/apps/tools/management/commands/importapp.py
djangox/apps/tools/management/commands/setupdeploy.py
djangox/apps/tools/management/commands/setupstatic.py
djangox/apps/tools/setupstatic/.bowerrc
djangox/apps/tools/setupstatic/bower.json
djangox/apps/unilogin/__init__.py
djangox/apps/unilogin/urls.py
djangox/apps/unilogin/controllers/__init__.py
djangox/apps/unilogin/controllers/accounts.py
djangox/apps/unilogin/templates/__init__.py
djangox/apps/unilogin/templates/unilogin/__init__.py
djangox/deploy/__init__.py
djangox/deploy/deployconfig_sample.py
djangox/deploy/fabfile.py
djangox/mako/__init__.py
djangox/mako/staticfiles.py
djangox/route/__init__.py
djangox/route/rest.py