Metadata-Version: 2.1
Name: djangox
Version: 0.1.19
Summary: Another way of using django. Convention over configuration for urls, mako template language support,json response, REST style API, convenient scripts, ...
Home-page: https://github.com/youngrok/djangox
Author: Youngrok Pak
Author-email: pak.youngrok@gmail.com
License: UNKNOWN
Keywords: rest route autodiscover django djangox mako
Platform: UNKNOWN
Classifier: Development Status :: 3 - Alpha
Classifier: Topic :: Software Development :: Libraries
Classifier: License :: OSI Approved :: BSD License
